mdbm.cpython-39-x86_64-linux-gnu.so
py_mdbm-0.1.1a1.dist-info/LICENSE
py_mdbm-0.1.1a1.dist-info/METADATA
py_mdbm-0.1.1a1.dist-info/WHEEL
py_mdbm-0.1.1a1.dist-info/top_level.txt
py_mdbm-0.1.1a1.dist-info/RECORD
py_mdbm.libs/libmdbm-fdae42cf.so.4
py_mdbm.libs/libcrypto-d9af65bd.so.1.1.1k
