Metadata-Version: 2.1
Name: py-mdbm
Version: 0.1.1a1
Summary: The Python interface to the MDBM key-value store.
Author-email: Torden <ioemen@gmail.com>
License: The MIT License (MIT)        
Project-URL: Homepage, https://github.com/torden/py-mdbm
Project-URL: Bug Tracker, https://github.com/torden/py-mdbm/issues
Classifier: Development Status :: 3 - Alpha
Classifier: Intended Audience :: Developers
Classifier: Intended Audience :: System Administrators
Classifier: License :: OSI Approved :: MIT License
Classifier: Topic :: Database
Classifier: Topic :: Database :: Database Engines/Servers
Classifier: Topic :: Utilities
Classifier: Programming Language :: C
Classifier: Programming Language :: Python :: 3
Classifier: License :: OSI Approved :: MIT License
Classifier: Operating System :: POSIX :: Linux
Requires-Python: >=3.7
License-File: LICENSE
